ramalama_sdk/__init__.py
ramalama_sdk/errors.py
ramalama_sdk/main.py
ramalama_sdk/py.typed
ramalama_sdk/schemas.py
ramalama_sdk/utils.py
ramalama_sdk-0.1.2.dist-info/METADATA
ramalama_sdk-0.1.2.dist-info/WHEEL
ramalama_sdk-0.1.2.dist-info/RECORD
