Metadata-Version: 2.4
Name: ramalama-sdk
Version: 0.1.2
Summary: An SDK for programmatically running local AI.
Project-URL: Repository, https://github.com/ramalama-labs/ramalama-sdks
Project-URL: Source, https://github.com/ramalama-labs/ramalama-sdks/tree/main/sdk/ramalama-python
Project-URL: Documentation, https://docs.ramalama.com/sdk/python
Author: Ramalama Labs
License: MIT
Requires-Python: >=3.10
Requires-Dist: ramalama
